tests/__init__.py
tests/load_pretrained_test.py
tests/modeling_albert_test.py
tests/modeling_bert_test.py
tests/adapters_tests/__init__.py
tests/adapters_tests/mengzi_adapter_test.py
tests/lm_tests/__init__.py
tests/lm_tests/mlm_test.py
tests/question_answering_tests/__init__.py
tests/question_answering_tests/callback_test.py
tests/question_answering_tests/models_test.py
tests/sentence_embedding_tests/__init__.py
tests/sentence_embedding_tests/bert_embedding_test.py
tests/sentence_embedding_tests/callback_test.py
tests/sentence_embedding_tests/simcse_models_test.py
tests/sequence_classification_tests/__init__.py
tests/sequence_classification_tests/models_test.py
tests/token_classification_tests/__init__.py
tests/token_classification_tests/callback_test.py
tests/token_classification_tests/crf_models_test.py
tests/token_classification_tests/models_test.py
transformers_keras/__init__.py
transformers_keras/client.py
transformers_keras/distiller.py
transformers_keras/modeling_albert.py
transformers_keras/modeling_bert.py
transformers_keras/modeling_utils.py
transformers_keras/adapters/__init__.py
transformers_keras/adapters/abstract_adapter.py
transformers_keras/adapters/adapter_factory.py
transformers_keras/adapters/albert_adapter.py
transformers_keras/adapters/bert_adapter.py
transformers_keras/adapters/mengzi_adapter.py
transformers_keras/common/__init__.py
transformers_keras/common/metrics.py
transformers_keras/common/utils.py
transformers_keras/lm/__init__.py
transformers_keras/lm/mlm.py
transformers_keras/question_answering/__init__.py
transformers_keras/question_answering/callback.py
transformers_keras/question_answering/models.py
transformers_keras/question_answering/readers.py
transformers_keras/sentence_embedding/__init__.py
transformers_keras/sentence_embedding/bert_embedding.py
transformers_keras/sentence_embedding/callback.py
transformers_keras/sentence_embedding/simcse_models.py
transformers_keras/sentiment_analysis/__init__.py
transformers_keras-0.5.1.dist-info/LICENSE
transformers_keras-0.5.1.dist-info/METADATA
transformers_keras-0.5.1.dist-info/WHEEL
transformers_keras-0.5.1.dist-info/top_level.txt
transformers_keras-0.5.1.dist-info/RECORD
