Metadata-Version: 2.1
Name: transformers-keras
Version: 0.5.1
Summary: Transformer-based models implemented in tensorflow 2.x(Keras)
Home-page: https://github.com/luozhouyang/transformers-keras
Author: ZhouYang Luo
Author-email: zhouyang.luo@gmail.com
License: Apache Software License
Platform: UNKNOWN
Classifier: Programming Language :: Python :: 3
Classifier: Programming Language :: Python :: 3.5
Classifier: Programming Language :: Python :: 3.6
Classifier: Programming Language :: Python :: 3.7
Classifier: Programming Language :: Python :: 3.8
Classifier: Programming Language :: Python :: 3.9
Classifier: License :: OSI Approved :: Apache Software License
Classifier: Operating System :: OS Independent
Classifier: Topic :: Scientific/Engineering :: Artificial Intelligence
License-File: LICENSE
Requires-Dist: tokenizers
Requires-Dist: tensorflow-addons[tensorflow]
Requires-Dist: seqeval
Requires-Dist: smile-datasets (==0.0.5)
